starlette_caches/__init__.py
starlette_caches/__version__.py
starlette_caches/decorators.py
starlette_caches/exceptions.py
starlette_caches/helpers.py
starlette_caches/middleware.py
starlette_caches/py.typed
starlette_caches/rules.py
starlette_caches/utils/__init__.py
starlette_caches/utils/cache.py
starlette_caches/utils/logging.py
starlette_caches/utils/misc.py
starlette_caches-0.4.1.dist-info/METADATA
starlette_caches-0.4.1.dist-info/WHEEL
starlette_caches-0.4.1.dist-info/licenses/LICENSE
starlette_caches-0.4.1.dist-info/RECORD
