Metadata-Version: 2.4
Name: starlette-caches
Version: 0.4.1
Summary: Server-side HTTP caching for ASGI applications, inspired by Django's cache framework
Project-URL: Repository, https://github.com/mattmess1221/starlette-caches
Project-URL: Documentation, https://mattmess1221.github.io/starlette-caches
Project-URL: Changelog, https://mattmess1221.github.io/starlette-caches/changelog
Project-URL: Issues, https://github.com/mattmess1221/starlette-caches/issues
Author-email: Matthew Messinger <mattmess1221@gmail.com>
License-Expression: MIT
License-File: LICENSE
Classifier: Development Status :: 3 - Alpha
Classifier: Intended Audience :: Developers
Classifier: License :: OSI Approved :: MIT License
Classifier: Operating System :: OS Independent
Classifier: Programming Language :: Python :: 3
Classifier: Programming Language :: Python :: 3.9
Classifier: Programming Language :: Python :: 3.10
Classifier: Programming Language :: Python :: 3.11
Classifier: Programming Language :: Python :: 3.12
Classifier: Programming Language :: Python :: 3.13
Classifier: Topic :: Internet :: WWW/HTTP
Classifier: Typing :: Typed
Requires-Python: >=3.9
Requires-Dist: aiocache>=0.12.3
Requires-Dist: starlette==0.*
Provides-Extra: memcached
Requires-Dist: aiomcache>=0.5.2; extra == 'memcached'
Provides-Extra: msgpack
Requires-Dist: msgpack>=0.5.5; extra == 'msgpack'
Provides-Extra: redis
Requires-Dist: redis>=5; extra == 'redis'
